dfselect/__init__.py
dfselect/context.py
dfselect/errors.py
dfselect/log.py
dfselect/util.py
dfselect/exec/__init__.py
dfselect/exec/expr.py
dfselect/exec/operator.py
dfselect/exec/udf.py
dfselect/parse/__init__.py
df_select-0.0.1.2.dist-info/METADATA
df_select-0.0.1.2.dist-info/WHEEL
df_select-0.0.1.2.dist-info/top_level.txt
df_select-0.0.1.2.dist-info/RECORD
